MANIFEST.in
README.md
VERSION
setup.py
EPSGlide.egg-info/PKG-INFO
EPSGlide.egg-info/SOURCES.txt
EPSGlide.egg-info/dependency_links.txt
EPSGlide.egg-info/top_level.txt
epsglide/__init__.py
epsglide/dataset.py
epsglide/geodesy.py
epsglide/src.py
epsglide/.dataset/Conversion/15593.json
epsglide/.dataset/Datum/6326.json
epsglide/.dataset/Ellipsoid/7030.json
epsglide/.dataset/GeodeticCoordRefSystem/4326.json
epsglide/.dataset/PrimeMeridian/8901.json
epsglide/.dataset/Unit/9001.json
epsglide/.dataset/Unit/9102.json
src/eqc.c
src/geoid.c
src/geoid.h
src/lcc.c
src/merc.c
src/miller.c
src/omerc.c
src/tmerc.c