Metadata-Version: 2.1
Name: EPSGlide
Version: 0.2.2
Summary: Efficient great circle computation and projection library with access to EPSG dataset public API
Home-page: https://moustikitos.github.io/python-epsg/
Author: Bruno THOORENS
Author-email: moustikitos@gmail.com
Maintainer: Bruno THOORENS
Maintainer-email: moustikitos@gmail.com
License: Copyright 2024, THOORENS Bruno, BSD licence
Project-URL: Bug Reports, https://github.com/Moustikitos/python-epsg/issues
Project-URL: Funding, https://github.com/Moustikitos/python-epsg?tab=readme-ov-file#support-this-project
Project-URL: Source, https://github.com/Moustikitos/python-epsg/
Keywords: epsg,projection,great,circle,geohash,georef,GARS,maidenhead,dataset
Classifier: Development Status :: 3 - Alpha
Classifier: Environment :: Console
Classifier: Intended Audience :: Developers
Classifier: Intended Audience :: Science/Research
Classifier: License :: OSI Approved :: BSD License
Classifier: Operating System :: Microsoft :: Windows
Classifier: Operating System :: POSIX :: Linux
Classifier: Programming Language :: C
Classifier: Programming Language :: Python :: 3
Classifier: Topic :: Scientific/Engineering :: GIS
Classifier: Topic :: Software Development :: Libraries :: Python Modules
